htmlement.py
htmlement-2.0.0.dist-info/LICENSE
htmlement-2.0.0.dist-info/METADATA
htmlement-2.0.0.dist-info/WHEEL
htmlement-2.0.0.dist-info/top_level.txt
htmlement-2.0.0.dist-info/RECORD
